CHANGES.txt
COPYRIGHT.txt
LICENSE.txt
MANIFEST.in
setup.py
van/__init__.py
van.timeformat.egg-info/PKG-INFO
van.timeformat.egg-info/SOURCES.txt
van.timeformat.egg-info/dependency_links.txt
van.timeformat.egg-info/namespace_packages.txt
van.timeformat.egg-info/not-zip-safe
van.timeformat.egg-info/requires.txt
van.timeformat.egg-info/top_level.txt
van/timeformat/README.txt
van/timeformat/__init__.py
van/timeformat/configure.zcml
van/timeformat/ftesting.zcml
van/timeformat/interfaces.py
van/timeformat/meta.zcml
van/timeformat/tales.py
van/timeformat/tests.py
van/timeformat/zcml.py
van/timeformat/zpt.txt