Metadata-Version: 1.0
Name: van.timeformat
Version: 1.1.1
Summary: Convienience functions for formatting dates/times using zope.i18n and TAL
Home-page: http://pypi.python.org/pypi/van.timeformat
Author: Vanguardistas LLC
Author-email: zope-dev@zope.org
License: ZPL 2.1
Platform: UNKNOWN
Classifier: Environment :: Web Environment
Classifier: Intended Audience :: Developers
Classifier: License :: OSI Approved :: Zope Public License
Classifier: Programming Language :: Python
Classifier: Topic :: Internet :: WWW/HTTP
Classifier: Framework :: Zope3
Classifier: Development Status :: 5 - Production/Stable
